to_delete/__init__.py
to_delete/__main__.py
to_delete-0.3.0.dist-info/AUTHORS.md
to_delete-0.3.0.dist-info/LICENSE
to_delete-0.3.0.dist-info/METADATA
to_delete-0.3.0.dist-info/WHEEL
to_delete-0.3.0.dist-info/entry_points.txt
to_delete-0.3.0.dist-info/top_level.txt
to_delete-0.3.0.dist-info/RECORD
